pyrapion/__init__.py
pyrapion/cli.py
pyrapion/energiscloud.py
pyrapion/pyrapion.py
pyrapion/quanstesx.py
pyrapion/redex.py
pyrapion/withphable.py
pyrapion/withphable_new.py
pyrapion-0.1.0.dist-info/licenses/AUTHORS.rst
pyrapion-0.1.0.dist-info/licenses/LICENSE
pyrapion-0.1.0.dist-info/METADATA
pyrapion-0.1.0.dist-info/WHEEL
pyrapion-0.1.0.dist-info/entry_points.txt
pyrapion-0.1.0.dist-info/top_level.txt
pyrapion-0.1.0.dist-info/RECORD
